Workbook

Sheet Hoja1
A1: direccion | B1: ciudad | C1: pdv | D1: ean_pdv | E1: Canal
A2: CL.7 # 2-40(B.CENTRO) | B2: EL BANCO | C2: DROGUERIA CENTRAL | D2: 14154 | E2: DROGUERIAS | F2: =VLOOKUP(D2,[1]Hoja3!$A$2:$E$15,5,FALSE) -> #N/A
A3: CR 50 # 22 - 41LOCAL 125 ( SALITRE ORIENTAL ) | B3: BOGOTA | C3: DROGUERIA CIPRESS PLAZA | D3: 14436 | E3: DROGUERIAS | F3: =VLOOKUP(D3,[1]Hoja3!$A$2:$E$15,5,FALSE) -> #N/A
A4: CLL 70A # 90 - 04 ( FLORIDA) | B4: BOGOTA | C4: KOLSUBDROGAS # 2 | D4: 14438 | E4: DROGUERIAS | F4: =VLOOKUP(D4,[1]Hoja3!$A$2:$E$15,5,FALSE) -> #N/A
A5: CR 101 # 72 - 27 (ALAMOS NORTE ) | B5: BOGOTA | C5: CIPRES #1 | D5: 14439 | E5: DROGUERIAS | F5: =VLOOKUP(D5,[1]Hoja3!$A$2:$E$15,5,FALSE) -> #N/A
A6: CR 104 # 64 - 22 ( EL MUELLE) | B6: BOGOTA | C6: DROGUERIA LABTOFAR | D6: 14440 | E6: DROGUERIAS | F6: =VLOOKUP(D6,[1]Hoja3!$A$2:$E$15,5,FALSE) -> #N/A
A7: CL.22 #48-66 (B.PRADOS DEL SALITRE) | B7: BOGOTA | C7: CAUCA # 2 | D7: 14441 | E7: DROGUERIAS | F7: =VLOOKUP(D7,[1]Hoja3!$A$2:$E$15,5,FALSE) -> #N/A
A8: CL.78 # 12-41(B.EL LAGO) | B8: BOGOTA | C8: CENTER LAGOS | D8: 14442 | E8: DROGUERIAS | F8: =VLOOKUP(D8,[1]Hoja3!$A$2:$E$15,5,FALSE) -> #N/A
A9: CR.11 # 92-20 (B.CHICO) | B9: BOGOTA | C9: DISNEY | D9: 14443 | E9: DROGUERIAS | F9: =VLOOKUP(D9,[1]Hoja3!$A$2:$E$15,5,FALSE) -> #N/A
A10: CRA 32A 25A 26 GRAN AMERICA | B10: BOGOTA | C10: DON JERONIMO | D10: 14445 | E10: DROGUERIAS | F10: =VLOOKUP(D10,[1]Hoja3!$A$2:$E$15,5,FALSE) -> #N/A
A11: CR 49 # 99 - 09 ( LA CASTELLANA) | B11: BOGOTA | C11: DROG. DROGAS LA NACIONAL # 4 | D11: 14446 | E11: DROGUERIAS | F11: =VLOOKUP(D11,[1]Hoja3!$A$2:$E$15,5,FALSE) -> #N/A
A12: CLL. 65 # 7 - 80 (QUINTA MACHO) | B12: BOGOTA | C12: DROG. FARMA GRANADA 2 | D12: 14448 | E12: DROGUERIAS | F12: =VLOOKUP(D12,[1]Hoja3!$A$2:$E$15,5,FALSE) -> #N/A
A13: CL.63C # 69P-05(B.BOSQUE POPULAR) | B13: BOGOTA | C13: DROG. M Y M | D13: 14449 | E13: DROGUERIAS | F13: =VLOOKUP(D13,[1]Hoja3!$A$2:$E$15,5,FALSE) -> #N/A
... A4146: CALLE 85 # 50-44 LOCAL 1 | B4146: BARRANQUILLA | C4146: FARMANORTE 39 | D4146: 20139 | E4146: DROGUERIAS | F4146: =VLOOKUP(D4146,[1]Hoja3!$A$2:$E$15,5,FALSE) -> #N/A
B4147: BARRANQUILLA | C4147: FARMANORTE 40 | D4147: 20140 | E4147: DROGUERIAS | F4147: =VLOOKUP(D4147,[1]Hoja3!$A$2:$E$15,5,FALSE) -> #N/A
A4148: CRA 45 CALLE 96 | B4148: BARRANQUILLA | C4148: FARMANORTE 43 | D4148: 20142 | E4148: DROGUERIAS | F4148: =VLOOKUP(D4148,[1]Hoja3!$A$2:$E$15,5,FALSE) -> #N/A
A4149: CALLE 106 N. 50 67 VILLA SANTOS | B4149: BARRANQUILLA | C4149: FARMANORTE 45 | D4149: 20144 | E4149: DROGUERIAS | F4149: =VLOOKUP(D4149,[1]Hoja3!$A$2:$E$15,5,FALSE) -> #N/A
A4150: CL 94 CON 52 | B4150: BARRANQUILLA | C4150: FARMANORTE 46 | D4150: 20145 | E4150: DROGUERIAS | F4150: =VLOOKUP(D4150,[1]Hoja3!$A$2:$E$15,5,FALSE) -> #N/A
A4151: CRA 28 1B-315 BLOQ UM LOCAL 206 CLINICA PORTO AZUL | B4151: BARRANQUILLA | C4151: FARMANORTE 48 | D4151: 20147 | E4151: DROGUERIAS | F4151: =VLOOKUP(D4151,[1]Hoja3!$A$2:$E$15,5,FALSE) -> #N/A
A4152: CALLE 19 # 6A-07 LOCAL 104 BARRIO SIMON BOLIVAR | B4152: BARRANQUILLA | C4152: FARMANORTE 49 | D4152: 20148 | E4152: DROGUERIAS | F4152: =VLOOKUP(D4152,[1]Hoja3!$A$2:$E$15,5,FALSE) -> #N/A
A4153: CARRERA 38 # 70-12 | B4153: BARRANQUILLA | C4153: FARMANORTE 53 | D4153: 20149 | E4153: DROGUERIAS | F4153: =VLOOKUP(D4153,[1]Hoja3!$A$2:$E$15,5,FALSE) -> #N/A
A4154: CALLE 94 CON 52 ESQUINA | B4154: BARRANQUILLA | C4154: FARMANORTE 62 | D4154: 20150 | E4154: DROGUERIAS | F4154: =VLOOKUP(D4154,[1]Hoja3!$A$2:$E$15,5,FALSE) -> #N/A
A4155: CALLE 19# 1D-06 BRR SIMON BOLIVAR | B4155: BARRANQUILLA | C4155: FARMANORTE 77 | D4155: 20154 | E4155: DROGUERIAS | F4155: =VLOOKUP(D4155,[1]Hoja3!$A$2:$E$15,5,FALSE) -> #N/A
B4156: SABANALARGA | C4156: FARMANORTE 79 | D4156: 20155 | E4156: DROGUERIAS | F4156: =VLOOKUP(D4156,[1]Hoja3!$A$2:$E$15,5,FALSE) -> #N/A
A4157: CALLE 71 # 41 - 71 LOCAL 1 | B4157: BARRANQUILLA | C4157: FARMANORTE 91 | D4157: 20156 | E4157: DROGUERIAS | F4157: =VLOOKUP(D4157,[1]Hoja3!$A$2:$E$15,5,FALSE) -> #N/A
A4158: CALLE 27C # 30-02 BRR HIPODROMO | B4158: SOLEDAD | C4158: FARMANORTE 99 | D4158: 20159 | E4158: DROGUERIAS | F4158: =VLOOKUP(D4158,[1]Hoja3!$A$2:$E$15,5,FALSE) -> #N/A
A4159: CLLE 16# 18 -35 | B4159: BARANOA | C4159: FARMAVIDA 72 | D4159: 20164 | E4159: DROGUERIAS | F4159: =VLOOKUP(D4159,[1]Hoja3!$A$2:$E$15,5,FALSE) -> #N/A
A4160: CRA 14B N0 77A -9 VILLA LOS ROBLES | B4160: SOLEDAD | C4160: FARMAVIDA 75 | D4160: 20166 | E4160: DROGUERIAS | F4160: =VLOOKUP(D4160,[1]Hoja3!$A$2:$E$15,5,FALSE) -> #N/A
A4161: KR 48 # 70-115 | B4161: BARRANQUILLA | C4161: FARMAVIDA NO. 04 | D4161: 20170 | E4161: DROGUERIAS | F4161: =VLOOKUP(D4161,[1]Hoja3!$A$2:$E$15,5,FALSE) -> #N/A
A4162: CL 96 # 45B - 58 LC.1 | B4162: BARRANQUILLA | C4162: FARMAVIDA NO. 05 | D4162: 20171 | E4162: DROGUERIAS | F4162: =VLOOKUP(D4162,[1]Hoja3!$A$2:$E$15,5,FALSE) -> #N/A
A4163: KR 49C # 80-13 | B4163: BARRANQUILLA | C4163: FARMAVIDA NO. 06 | D4163: 20172 | E4163: DROGUERIAS | F4163: =VLOOKUP(D4163,[1]Hoja3!$A$2:$E$15,5,FALSE) -> #N/A
A4164: CL 84 # 50-17 LC.1 | B4164: BARRANQUILLA | C4164: FARMAVIDA NO. 08 | D4164: 20173 | E4164: DROGUERIAS | F4164: =VLOOKUP(D4164,[1]Hoja3!$A$2:$E$15,5,FALSE) -> #N/A
A4165: CL 72 # 48-05 ESQUINA | B4165: BARRANQUILLA | C4165: FARMAVIDA NO. 13 | D4165: 20178 | E4165: DROGUERIAS | F4165: =VLOOKUP(D4165,[1]Hoja3!$A$2:$E$15,5,FALSE) -> #N/A
A4166: CL 44 # 8-07 | B4166: BARRANQUILLA | C4166: FARMAVIDA NO. 14 | D4166: 20179 | E4166: DROGUERIAS | F4166: =VLOOKUP(D4166,[1]Hoja3!$A$2:$E$15,5,FALSE) -> #N/A
A4167: KM 7 ANTIGUA VIA PTO. COLOMBIA | B4167: PUERTO COLOMBIA | C4167: FARMAVIDA NO. 17 | D4167: 20182 | E4167: DROGUERIAS | F4167: =VLOOKUP(D4167,[1]Hoja3!$A$2:$E$15,5,FALSE) -> #N/A
A4168: CL 86 # 50-158 LC.3 | B4168: BARRANQUILLA | C4168: FARMAVIDA NO. 25 | D4168: 20188 | E4168: DROGUERIAS | F4168: =VLOOKUP(D4168,[1]Hoja3!$A$2:$E$15,5,FALSE) -> #N/A
... A4192: CALLE 78 NO. 53 - 70 LOCAL 116 CENTRO COMERCIAL VILLA COUNTRY | B4192: BARRANQUILLA | C4192: INGLESA 141 | D4192: 20235 | E4192: DROGUERIAS | F4192: =VLOOKUP(D4192,[1]Hoja3!$A$2:$E$15,5,FALSE) -> #N/A
B4193: BARRANQUILLA | C4193: INGLESA 153 | D4193: 20236 | E4193: DROGUERIAS | F4193: =VLOOKUP(D4193,[1]Hoja3!$A$2:$E$15,5,FALSE) -> #N/A
A4194: CALLE 72 NO. 43 - 7 | B4194: BARRANQUILLA | C4194: INGLESA 172 | D4194: 20237 | E4194: DROGUERIAS | F4194: =VLOOKUP(D4194,[1]Hoja3!$A$2:$E$15,5,FALSE) -> #N/A
A4195: CARRERA 43 NO. 68-13 ESTACIN DE SERVICIO SAN JORGE | B4195: BARRANQUILLA | C4195: INGLESA 191 | D4195: 20238 | E4195: DROGUERIAS | F4195: =VLOOKUP(D4195,[1]Hoja3!$A$2:$E$15,5,FALSE) -> #N/A
A4196: CALLE 80 # 53-18 LC 6-7 PARQUE WASHINGTON | B4196: BARRANQUILLA | C4196: INGLESA 199 | D4196: 20239 | E4196: DROGUERIAS | F4196: =VLOOKUP(D4196,[1]Hoja3!$A$2:$E$15,5,FALSE) -> #N/A
A4197: CARRERA 47 N. 70 10 PRADO NORTE | B4197: BARRANQUILLA | C4197: INGLESA 20 | D4197: 20240 | E4197: DROGUERIAS | F4197: =VLOOKUP(D4197,[1]Hoja3!$A$2:$E$15,5,FALSE) -> #N/A
A4198: CALLE 141 NO 46C 23 | B4198: BARRANQUILLA | C4198: INGLESA 238 | D4198: 20247 | E4198: DROGUERIAS | F4198: =VLOOKUP(D4198,[1]Hoja3!$A$2:$E$15,5,FALSE) -> #N/A
A4199: CALLE 16 N 19-05 | B4199: BARANOA | C4199: INGLESA 254 | D4199: 20250 | E4199: DROGUERIAS | F4199: =VLOOKUP(D4199,[1]Hoja3!$A$2:$E$15,5,FALSE) -> #N/A
A4200: CRA 12#63-79 | B4200: BARRANQUILLA | C4200: INGLESA 269 | D4200: 20251 | E4200: DROGUERIAS | F4200: =VLOOKUP(D4200,[1]Hoja3!$A$2:$E$15,5,FALSE) -> #N/A
A4201: CARRERA 38 NO 108- 57 | B4201: BARRANQUILLA | C4201: INGLESA 302 | D4201: 20255 | E4201: DROGUERIAS | F4201: =VLOOKUP(D4201,[1]Hoja3!$A$2:$E$15,5,FALSE) -> #N/A
A4202: CALLE 82 NO. 46-58 LOCAL 1 | B4202: BARRANQUILLA | C4202: INGLESA 46 | D4202: 20259 | E4202: DROGUERIAS | F4202: =VLOOKUP(D4202,[1]Hoja3!$A$2:$E$15,5,FALSE) -> #N/A
A4203: CARRERA 30 CALLE 1 NO. 18-41 CORREDOR UNIVERSITARIO CC-LCHAMP | B4203: PUERTO COLOMBIA | C4203: INGLESA 47 | D4203: 20260 | E4203: DROGUERIAS | F4203: =VLOOKUP(D4203,[1]Hoja3!$A$2:$E$15,5,FALSE) -> #N/A
A4204: CALLE 19 N 17 38 | B4204: BARANOA | C4204: INGLESA 54 | D4204: 20261 | E4204: DROGUERIAS | F4204: =VLOOKUP(D4204,[1]Hoja3!$A$2:$E$15,5,FALSE) -> #N/A
A4205: CARRERA 12 SUR NO. 43-38 CIUDADELA 20 DE JULIO | B4205: BARRANQUILLA | C4205: INGLESA 63 | D4205: 20262 | E4205: DROGUERIAS | F4205: =VLOOKUP(D4205,[1]Hoja3!$A$2:$E$15,5,FALSE) -> #N/A
... A5054: CL.7 # 12-29 (B. CENTRO) | B5054: CIRCASIA | C5054: DROGUERIA CUYABRA # 3 | D5054: 21552 | E5054: DROGUERIAS | F5054: =VLOOKUP(D5054,[1]Hoja3!$A$2:$E$15,5,FALSE) -> #N/A
B5055: CIRCASIA | C5055: DROGUERIA QUINDIO #2 | D5055: 21553 | E5055: DROGUERIAS | F5055: =VLOOKUP(D5055,[1]Hoja3!$A$2:$E$15,5,FALSE) -> #N/A
A5056: CL. 10 A 23 26 | B5056: ARMENIA | C5056: DROGUERIA DROGUISALUD DEL GRANADA | D5056: 21555 | E5056: DROGUERIAS | F5056: =VLOOKUP(D5056,[1]Hoja3!$A$2:$E$15,5,FALSE) -> #N/A
A5057: CL.35 # 22 - 04 ESQ. (B. SANTANDER) | B5057: ARMENIA | C5057: DROGUERIA DTODOS | D5057: 21557 | E5057: DROGUERIAS | F5057: =VLOOKUP(D5057,[1]Hoja3!$A$2:$E$15,5,FALSE) -> #N/A
A5058: CR.2 #1-180 CORREGIMIENTO EL CAIMO | B5058: ARMENIA | C5058: DROGUERIA EL CAIMO | D5058: 21558 | E5058: DROGUERIAS | F5058: =VLOOKUP(D5058,[1]Hoja3!$A$2:$E$15,5,FALSE) -> #N/A
A5059: CR 27 NRO 32 09 | B5059: CALARCA | C5059: DROGUERIA EL CAMPESINO | D5059: 21559 | E5059: DROGUERIAS | F5059: =VLOOKUP(D5059,[1]Hoja3!$A$2:$E$15,5,FALSE) -> #N/A
A5060: MZA 2 CASA 12 (B. LA ESMERALDA) | B5060: ARMENIA | C5060: DROGUERIA EL CUYABRITO | D5060: 21560 | E5060: DROGUERIAS | F5060: =VLOOKUP(D5060,[1]Hoja3!$A$2:$E$15,5,FALSE) -> #N/A
A5061: AV COLON #17-25 | B5061: CALARCA | C5061: DROGUERIA EL DESCUENTO ERL | D5061: 21562 | E5061: DROGUERIAS | F5061: =VLOOKUP(D5061,[1]Hoja3!$A$2:$E$15,5,FALSE) -> #N/A
A5062: AV.COLON # 21-467 LC.2 | B5062: CALARCA | C5062: DROGUERIA EL NEGRITO # 5 | D5062: 21563 | E5062: DROGUERIAS | F5062: =VLOOKUP(D5062,[1]Hoja3!$A$2:$E$15,5,FALSE) -> #N/A
A5063: CL.39 # 27-28(B.CENTRO) | B5063: CALARCA | C5063: DROGUERIA EL NEGRITO 4 | D5063: 21564 | E5063: DROGUERIAS | F5063: =VLOOKUP(D5063,[1]Hoja3!$A$2:$E$15,5,FALSE) -> #N/A
A5064: CL.38 # 27-11(B.PLAZA DE MERCADO) | B5064: CALARCA | C5064: DROGUERIA EL NEGRITO NATURISTA | D5064: 21565 | E5064: DROGUERIAS | F5064: =VLOOKUP(D5064,[1]Hoja3!$A$2:$E$15,5,FALSE) -> #N/A
A5065: BRRO 7 DE AGOSTO MZ 7 CS 3 | B5065: ARMENIA | C5065: DROGUERIA EL OFERTAZO | D5065: 21566 | E5065: DROGUERIAS | F5065: =VLOOKUP(D5065,[1]Hoja3!$A$2:$E$15,5,FALSE) -> #N/A
A5066: MZ.30 CS.7 (B. CIUDAD DORADA) | B5066: ARMENIA | C5066: DROGUERIA ESPECIAL CRS | D5066: 21568 | E5066: DROGUERIAS | F5066: =VLOOKUP(D5066,[1]Hoja3!$A$2:$E$15,5,FALSE) -> #N/A
A5067: CR.7# 20- 22 LC 2 | B5067: MONTENEGRO | C5067: DROGUERIA ESTELAR | D5067: 21569 | E5067: DROGUERIAS | F5067: =VLOOKUP(D5067,[1]Hoja3!$A$2:$E$15,5,FALSE) -> #N/A
... A5150: CR.12 CL.11 ESQUINA (B. GALERIA) | B5150: ZARZAL | C5150: FARMASALUD DROGUERIAS EA | D5150: 21670 | E5150: DROGUERIAS | F5150: =VLOOKUP(D5150,[1]Hoja3!$A$2:$E$15,5,FALSE) -> #N/A
B5151: ARMENIA | C5151: FARMA SUR MC DROGUERIA | D5151: 21671 | E5151: DROGUERIAS | F5151: =VLOOKUP(D5151,[1]Hoja3!$A$2:$E$15,5,FALSE) -> #N/A
A5152: CR.18 # 19-57 (CENTRO) | B5152: ARMENIA | C5152: MIL DROGAS LTDA. | D5152: 21675 | E5152: DROGUERIAS | F5152: =VLOOKUP(D5152,[1]Hoja3!$A$2:$E$15,5,FALSE) -> #N/A
A5153: CR.9 #11-11 | B5153: ZARZAL | C5153: PHARMAMEDI 1 DROGUERIAS | D5153: 21676 | E5153: DROGUERIAS | F5153: =VLOOKUP(D5153,[1]Hoja3!$A$2:$E$15,5,FALSE) -> #N/A
A5154: CR.50 CL.50-06 P.1 DE SEVILLA (B.CE | B5154: SEVILLA | C5154: POPULAR (DROGUERIA) | D5154: 21677 | E5154: DROGUERIAS | F5154: =VLOOKUP(D5154,[1]Hoja3!$A$2:$E$15,5,FALSE) -> #N/A
A5155: KM.10 VIA AEREOPUERTO EL EDEN LC.5 | B5155: ARMENIA | C5155: PROFAMILIAR MALL PARAISO | D5155: 21678 | E5155: DROGUERIAS | F5155: =VLOOKUP(D5155,[1]Hoja3!$A$2:$E$15,5,FALSE) -> #N/A
A5156: CL.49 # 50-10 (B.CENTRO) | B5156: SEVILLA | C5156: SEVIDROGAS | D5156: 21680 | E5156: DROGUERIAS | F5156: =VLOOKUP(D5156,[1]Hoja3!$A$2:$E$15,5,FALSE) -> #N/A
A5157: MZ.33 # 9-10 (B.LA PATRIA) | B5157: ARMENIA | C5157: TU SALUD | D5157: 21682 | E5157: DROGUERIAS | F5157: =VLOOKUP(D5157,[1]Hoja3!$A$2:$E$15,5,FALSE) -> #N/A
A5158: CARRERA 23 NO. 53A - 04 Y 14 | B5158: MANIZALES | C5158: ALEMANA 127 | D5158: 21683 | E5158: DROGUERIAS | F5158: =VLOOKUP(D5158,[1]Hoja3!$A$2:$E$15,5,FALSE) -> #N/A
A5159: CALLE 11 NO 8-20 | B5159: CHINCHINA | C5159: ALEMANA 258 | D5159: 21684 | E5159: DROGUERIAS | F5159: =VLOOKUP(D5159,[1]Hoja3!$A$2:$E$15,5,FALSE) -> #N/A
A5160: CARRERA. 23 NO 20-50 | B5160: MANIZALES | C5160: ALEMANA 265 | D5160: 21685 | E5160: DROGUERIAS | F5160: =VLOOKUP(D5160,[1]Hoja3!$A$2:$E$15,5,FALSE) -> #N/A
A5161: CARRERA 23 NO. 60-98 PLAZA SANTO DOMINGO | B5161: MANIZALES | C5161: ALEMANA 93 | D5161: 21686 | E5161: DROGUERIAS | F5161: =VLOOKUP(D5161,[1]Hoja3!$A$2:$E$15,5,FALSE) -> #N/A
A5162: CR.7 # 32-37 | B5162: SUPIA | C5162: CAFIDROGAS SUPIA | D5162: 21687 | E5162: DROGUERIAS | F5162: =VLOOKUP(D5162,[1]Hoja3!$A$2:$E$15,5,FALSE) -> #N/A
A5163: CR.20 CL.75 ESQ. | B5163: MANIZALES | C5163: CALDAS | D5163: 21688 | E5163: DROGUERIAS | F5163: =VLOOKUP(D5163,[1]Hoja3!$A$2:$E$15,5,FALSE) -> #N/A
... A5237: CLL 23 20-19 CENTRO | B5237: MANIZALES | C5237: DROGUERIA FARMICENTRO | D5237: 21773 | E5237: DROGUERIAS | F5237: =VLOOKUP(D5237,[1]Hoja3!$A$2:$E$15,5,FALSE) -> #N/A
B5238: MANIZALES | C5238: FARMALIFE PERALONSO | D5238: 21774 | E5238: DROGUERIAS | F5238: =VLOOKUP(D5238,[1]Hoja3!$A$2:$E$15,5,FALSE) -> #N/A
A5239: CARRERA 7 NRO. 12 - 68 | B5239: CHINCHINA | C5239: DROGUERIA LA ESTACION | D5239: 21775 | E5239: DROGUERIAS | F5239: =VLOOKUP(D5239,[1]Hoja3!$A$2:$E$15,5,FALSE) -> #N/A
A5240: CR.36 CL.96 ESQUINA (B.ENEA) | B5240: MANIZALES | C5240: DROGUERIA LA NUBIA MANIZALES | D5240: 21776 | E5240: DROGUERIAS | F5240: =VLOOKUP(D5240,[1]Hoja3!$A$2:$E$15,5,FALSE) -> #N/A
A5241: CR.12 # 62A-43(B.VIVEROS) | B5241: MANIZALES | C5241: DROGUERIA MERDROGAS MANIZALES # 2 | D5241: 21779 | E5241: DROGUERIAS | F5241: =VLOOKUP(D5241,[1]Hoja3!$A$2:$E$15,5,FALSE) -> #N/A
A5242: CL.18 # 27-72 ( B. EL CARMEN) | B5242: MANIZALES | C5242: DROGUERIA PAM | D5242: 21781 | E5242: DROGUERIAS | F5242: =VLOOKUP(D5242,[1]Hoja3!$A$2:$E$15,5,FALSE) -> #N/A
A5243: CR.20 # 17-30 (B.CENTRO) | B5243: MANIZALES | C5243: DROGUERIA PHARMASIEL | D5243: 21782 | E5243: DROGUERIAS | F5243: =VLOOKUP(D5243,[1]Hoja3!$A$2:$E$15,5,FALSE) -> #N/A
A5244: CL.9 # 8 - 04 (B. CENTRO) | B5244: NEIRA | C5244: DROGUERIA PRINCIPAL NEIRA | D5244: 21783 | E5244: DROGUERIAS | F5244: =VLOOKUP(D5244,[1]Hoja3!$A$2:$E$15,5,FALSE) -> #N/A
A5245: CL.13 E # 48 E - 16 (B. SAN CAYETAN | B5245: MANIZALES | C5245: DROGUERIA PROSALUD SAN CAYETANO | D5245: 21784 | E5245: DROGUERIAS | F5245: =VLOOKUP(D5245,[1]Hoja3!$A$2:$E$15,5,FALSE) -> #N/A
A5246: CR.23 # 30-29 CENTRO | B5246: MANIZALES | C5246: DROGUERIA SAN FRANCISCO # 1 | D5246: 21787 | E5246: DROGUERIAS | F5246: =VLOOKUP(D5246,[1]Hoja3!$A$2:$E$15,5,FALSE) -> #N/A
A5247: CR. 10 # 65 B -31 (B. LA SULTANA) | B5247: MANIZALES | C5247: DROGUERIA SAN MARTIN DE PORRAS | D5247: 21789 | E5247: DROGUERIAS | F5247: =VLOOKUP(D5247,[1]Hoja3!$A$2:$E$15,5,FALSE) -> #N/A
A5248: CL.57F # 11-04 PS.1 LC.1 | B5248: MANIZALES | C5248: DROGUERIA SAN MARTIN DE PORRAS #2 | D5248: 21790 | E5248: DROGUERIAS | F5248: =VLOOKUP(D5248,[1]Hoja3!$A$2:$E$15,5,FALSE) -> #N/A
A5249: CL.57F # 10D-04(B.CAROLA) | B5249: MANIZALES | C5249: DROGUERIA SANTA CRUZ MANIZALES | D5249: 21791 | E5249: DROGUERIAS | F5249: =VLOOKUP(D5249,[1]Hoja3!$A$2:$E$15,5,FALSE) -> #N/A
A5250: CR.22 # 25-03 (B. CENTRO) | B5250: MANIZALES | C5250: DROGUERIA SANTA INES | D5250: 21792 | E5250: DROGUERIAS | F5250: =VLOOKUP(D5250,[1]Hoja3!$A$2:$E$15,5,FALSE) -> #N/A
... A6546: CL9#23-01(B.SANJOSE) | B6546: BOGOTA | C6546: HIPERDROGUERIA FARMACOS 5 | D6546: 39231 | E6546: DROGUERIAS | F6546: =VLOOKUP(D6546,[1]Hoja3!$A$2:$E$15,5,FALSE) -> #N/A
B6547: MEDELLIN | C6547: DROGUERIA FARMAZO | D6547: 39236 | E6547: DROGUERIAS | F6547: =VLOOKUP(D6547,[1]Hoja3!$A$2:$E$15,5,FALSE) -> #N/A
B6548: MEDELLIN | C6548: DROGUERIA GOLONDRINAS | D6548: 39237 | E6548: DROGUERIAS | F6548: =VLOOKUP(D6548,[1]Hoja3!$A$2:$E$15,5,FALSE) -> #N/A
A6549: CALLE 98 #70 - 09 | B6549: MEDELLIN | C6549: DROG EL DESCANSO | D6549: 39241 | E6549: DROGUERIAS | F6549: =VLOOKUP(D6549,[1]Hoja3!$A$2:$E$15,5,FALSE) -> #N/A
B6550: MEDELLIN | C6550: DROG GOLDMAN | D6550: 39242 | E6550: DROGUERIAS | F6550: =VLOOKUP(D6550,[1]Hoja3!$A$2:$E$15,5,FALSE) -> #N/A
A6551: CALLE 92 EE #69-10 | B6551: MEDELLIN | C6551: DROG LA MARIA | D6551: 39243 | E6551: DROGUERIAS | F6551: =VLOOKUP(D6551,[1]Hoja3!$A$2:$E$15,5,FALSE) -> #N/A
A6552: CL62#129-77SANCRISTOBAL | B6552: MEDELLIN | C6552: DROG SANARE SC | D6552: 39245 | E6552: DROGUERIAS | F6552: =VLOOKUP(D6552,[1]Hoja3!$A$2:$E$15,5,FALSE) -> #N/A
B6553: MEDELLIN | C6553: METRODESCUENTOS | D6553: 39248 | E6553: DROGUERIAS | F6553: =VLOOKUP(D6553,[1]Hoja3!$A$2:$E$15,5,FALSE) -> #N/A
...

Sheet Hoja2
A1: direccion | B1: ciudad | C1: pdv | D1: ean_pdv | E1: Canal
A2: CALLE 19 NO. 19-99 | B2: BARANOA | C2: REBAJA PLUS 147 No. 1 BARANOA CENTRO | D2: 7707630000000 | E2: MODERNO | F2: REBAJA PLUS 147 No. 1 BARANOA CENTRO | G2: =VLOOKUP(D2,Hoja1!D:D,1,0) -> #N/A
A3: CALLE 57 NO. 23-47 | B3: BARRANQUILLA | C3: REBAJA PLUS 196 No. 34 BARRANQUILLA LOS ANDES | D3: 7707630000000 | E3: MODERNO | F3: REBAJA PLUS 196 No. 34 BARRANQUILLA LOS ANDES | G3: =VLOOKUP(D3,Hoja1!D:D,1,0) -> #N/A
A4: CARRERA 19 NO. 18-03 ESQUINA | B4: BARANOA | C4: REBAJA PLUS 1N4 No. 2 BARANOA CENTRO | D4: 7707630000000 | E4: MODERNO | F4: REBAJA PLUS 1N4 No. 2 BARANOA CENTRO | G4: =VLOOKUP(D4,Hoja1!D:D,1,0) -> #N/A
A5: KR 9 10 55 BERLIN | B5: PEREIRA | C5: SÚPER BOOM LA 10 | D5: 27329 | E5: TRADICIONAL | F5: SÚPER BOOM LA 10 | G5: =VLOOKUP(D5,Hoja1!D:D,1,0) -> #N/A
A6: KR 8 38 75 CENTRO | B6: PEREIRA | C6: SUPER BOON LA 39 | D6: 27324 | E6: TRADICIONAL | F6: SUPER BOON LA 39 | G6: =VLOOKUP(D6,Hoja1!D:D,1,0) -> #N/A
A7: CL 39 27 12 GALERIA | B7: CALARCA | C7: SUPERMERCADO EL PROGRESO | D7: 27259 | E7: TRADICIONAL | F7: SUPERMERCADO EL PROGRESO | G7: =VLOOKUP(D7,Hoja1!D:D,1,0) -> #N/A
A8: CL 22 14 31 LAURELES | B8: ARMENIA | C8: SUPERMERCADO LAURELES | D8: 27680 | E8: TRADICIONAL | F8: SUPERMERCADO LAURELES | G8: =VLOOKUP(D8,Hoja1!D:D,1,0) -> #N/A
